cffi_buildtool-1.1.1.dist-info/METADATA
cffi_buildtool-1.1.1.dist-info/WHEEL
cffi_buildtool-1.1.1.dist-info/entry_points.txt
cffi_buildtool/__init__.py
cffi_buildtool/__main__.py
cffi_buildtool/cli.py
cffi_buildtool/gen.py
cffi_buildtool-1.1.1.dist-info/RECORD
