Metadata-Version: 2.1
Name: cffi-buildtool
Version: 1.1.1
Summary: CFFI Buildtool helps build CFFI-based Python extension modules without setuptools.
Author-Email: Rose Davidson <rose@metaclassical.com>
Classifier: Development Status :: 5 - Production/Stable
Classifier: Intended Audience :: Developers
Classifier: License :: OSI Approved :: MIT License
Classifier: Operating System :: Unix
Classifier: Operating System :: POSIX
Classifier: Operating System :: Microsoft :: Windows
Classifier: Programming Language :: Python
Classifier: Programming Language :: Python :: 3
Classifier: Programming Language :: Python :: 3 :: Only
Classifier: Programming Language :: Python :: 3.8
Classifier: Programming Language :: Python :: 3.9
Classifier: Programming Language :: Python :: 3.10
Classifier: Programming Language :: Python :: 3.11
Classifier: Programming Language :: Python :: 3.12
Classifier: Programming Language :: Python :: Implementation :: CPython
Classifier: Programming Language :: Python :: Implementation :: PyPy
Project-URL: Changelog, https://github.com/inklesspen/cffi-buildtool/blob/main/CHANGELOG.md
Project-URL: Documentation, https://github.com/inklesspen/cffi-buildtool/blob/main/README.md
Project-URL: Issues, https://github.com/inklesspen/cffi-buildtool/issues
Project-URL: Repository, https://github.com/inklesspen/cffi-buildtool.git
Requires-Python: >=3.8
Requires-Dist: cffi>=1.17.1
